fine_python_virtualenv/__init__.py
fine_python_virtualenv/prepare_envs_handler.py
fine_python_virtualenv/prepare_runners_handler.py
fine_python_virtualenv-0.1.0.dist-info/METADATA
fine_python_virtualenv-0.1.0.dist-info/WHEEL
fine_python_virtualenv-0.1.0.dist-info/top_level.txt
fine_python_virtualenv-0.1.0.dist-info/RECORD
