Metadata-Version: 2.4
Name: fine-python-virtualenv
Version: 0.1.0
Author-email: Vladyslav Hnatiuk <aders1234@gmail.com>
Requires-Python: <3.14,>=3.11
Requires-Dist: finecode_extension_api==0.3.*
Requires-Dist: virtualenv<21.0.0,>=20.0.0
